{
    "encomendas": [
        {
            "nome": "BMW",
            "produto": "M3",
            "qtde": 3,
            "unit": 800,
            "total": 0
        },
        {
            "nome": "Mercedes-Benz",
            "produto": "amg GLE",
            "qtde": 2,
            "unit": 1000,
            "total": 0
        },
        {
            "nome": "Jeep",
            "produto": "Renegade",
            "qtde": 1,
            "unit": 700,
            "total": 0
        },
        {
            "nome": "Honda",
            "produto": "HR-V",
            "qtde": 5,
            "unit": 600,
            "total": 0
        },
        {
            "nome": "Mitsubishi",
            "produto": "Lancer Evolution",
            "qtde": 5,
            "unit": 650,
            "total": 0
        }
    ]
}